{"armature":[{"slot":[{"color":{},"name":"mart","parent":"mart"},{"z":1,"color":{},"name":"denglong1","parent":"denglong1"},{"z":2,"color":{},"name":"denglong2","parent":"denglong2"},{"z":3,"color":{},"name":"zhezhao","parent":"zhezhao"},{"blendMode":"add","z":4,"color":{},"name":"mart_0","parent":"mart_0"},{"blendMode":"add","z":5,"color":{},"name":"denglong1_0","parent":"denglong1_0"},{"blendMode":"add","z":6,"color":{},"name":"denglong2_0","parent":"denglong2_0"},{"blendMode":"add","z":7,"color":{},"name":"zhezhao_0","parent":"zhezhao_0"},{"blendMode":"add","z":8,"color":{},"name":"diejiaguang","parent":"diejiaguang"},{"blendMode":"add","z":9,"color":{},"name":"diejiaguang2","parent":"diejiaguang2"}],"defaultActions":[{"gotoAndPlay":"action1"}],"ik":[],"type":"Armature","frameRate":30,"skin":[{"slot":[{"display":[{"type":"image","name":"texture_blackmart/denglong1","transform":{"y":32,"x":0.5}}],"blendMode":"add","name":"denglong1_0"},{"display":[{"type":"image","name":"texture_blackmart/denglong2","transform":{"y":36}}],"blendMode":"add","name":"denglong2_0"},{"display":[{"type":"image","name":"texture_blackmart/mart","transform":{"y":-73}}],"blendMode":"add","name":"mart_0"},{"display":[{"type":"image","name":"diejiaguang","transform":{"y":0.35,"x":0.4}}],"blendMode":"add","name":"diejiaguang"},{"display":[{"type":"image","name":"texture_blackmart/mart","transform":{"y":-73}}],"name":"mart"},{"display":[{"type":"image","name":"diejiaguang","transform":{"y":0.35,"x":0.4}}],"blendMode":"add","name":"diejiaguang2"},{"display":[{"type":"image","name":"texture_blackmart/denglong1","transform":{"y":32,"x":0.5}}],"name":"denglong1"},{"display":[{"type":"image","name":"texture_blackmart/zhezhao","transform":{}}],"blendMode":"add","name":"zhezhao_0"},{"display":[{"type":"image","name":"texture_blackmart/denglong2","transform":{"y":36}}],"name":"denglong2"},{"display":[{"type":"image","name":"texture_blackmart/zhezhao","transform":{}}],"name":"zhezhao"}],"name":""}],"bone":[{"name":"root","transform":{}},{"transform":{"y":-159.2,"skY":29.99,"skX":29.99,"scX":2.52,"scY":3.88,"x":99.7},"name":"diejiaguang2","parent":"root"},{"transform":{"y":-193.5,"skY":-5.97,"skX":-5.97,"x":120.05},"name":"denglong1","parent":"root"},{"transform":{"y":-157.95,"skY":-5.69,"skX":-5.69,"x":217.55},"name":"denglong2","parent":"root"},{"transform":{"y":-183,"scX":2,"scY":2,"x":208.05},"name":"zhezhao","parent":"root"},{"transform":{"y":-117.5,"scX":2.59,"scY":3.99,"x":219.1},"name":"diejiaguang","parent":"root"},{"transform":{"y":-66.5,"x":223},"name":"mart","parent":"root"},{"transform":{"y":-64.6,"scX":1.03,"scY":0.95,"x":223},"name":"mart_0","parent":"root"},{"transform":{"y":-193.35,"skY":36.97,"skX":33.23,"scX":1.03,"scY":0.95,"x":119.25},"name":"denglong1_0","parent":"root"},{"transform":{"y":-151.55,"skY":-37.3,"skX":-34.13,"scX":1.03,"scY":0.95,"x":217.35},"name":"denglong2_0","parent":"root"},{"transform":{"y":-175.35,"scX":2.06,"scY":1.9,"x":207.55},"name":"zhezhao_0","parent":"root"}],"name":"blackmart","animation":[{"slot":[{"frame":[{"duration":19,"tweenEasing":0,"displayIndex":-1,"color":{}},{"duration":20,"tweenEasing":0,"color":{"aM":0}},{"duration":20,"tweenEasing":0,"color":{}},{"duration":1,"tweenEasing":null,"color":{"aM":0}},{"duration":19,"tweenEasing":null,"displayIndex":-1,"color":{}}],"name":"diejiaguang2"},{"frame":[{"duration":19,"tweenEasing":0,"color":{}},{"duration":1,"tweenEasing":null,"color":{"aM":0}},{"duration":39,"tweenEasing":0,"displayIndex":-1,"color":{}},{"duration":20,"tweenEasing":0,"color":{"aM":0}},{"duration":0,"tweenEasing":null,"color":{}}],"name":"diejiaguang"},{"frame":[{"duration":79,"tweenEasing":0,"color":{}},{"duration":0,"tweenEasing":null,"color":{}}],"name":"zhezhao"},{"frame":[{"duration":19,"tweenEasing":0,"color":{}},{"duration":20,"tweenEasing":0,"color":{}},{"duration":20,"tweenEasing":0,"color":{}},{"duration":20,"tweenEasing":0,"color":{}},{"duration":0,"tweenEasing":null,"color":{}}],"name":"denglong2"},{"frame":[{"duration":19,"tweenEasing":0,"color":{}},{"duration":20,"tweenEasing":0,"color":{}},{"duration":20,"tweenEasing":0,"color":{}},{"duration":20,"tweenEasing":0,"color":{}},{"duration":0,"tweenEasing":null,"color":{}}],"name":"denglong1"},{"frame":[{"duration":79,"tweenEasing":0,"color":{}},{"duration":0,"tweenEasing":null,"color":{}}],"name":"mart"},{"frame":[{"duration":79,"tweenEasing":null,"displayIndex":-1,"color":{}}],"name":"mart_0"},{"frame":[{"duration":79,"tweenEasing":null,"displayIndex":-1,"color":{}}],"name":"denglong1_0"},{"frame":[{"duration":79,"tweenEasing":null,"displayIndex":-1,"color":{}}],"name":"denglong2_0"},{"frame":[{"duration":79,"tweenEasing":null,"displayIndex":-1,"color":{}}],"name":"zhezhao_0"}],"frame":[],"duration":79,"bone":[{"frame":[{"duration":79,"tweenEasing":0,"transform":{}},{"duration":0,"tweenEasing":null,"transform":{}}],"name":"mart"},{"frame":[{"duration":19,"tweenEasing":0,"transform":{}},{"duration":20,"tweenEasing":0,"transform":{"y":-0.05,"skY":2.84,"skX":4.22,"scX":0.98,"scY":1.01,"x":0.05}},{"duration":20,"tweenEasing":0,"transform":{"skY":11.68,"skX":11.68}},{"duration":20,"tweenEasing":0,"transform":{"y":-0.05,"skY":7.32,"skX":4.44,"scX":1.03,"scY":0.99,"x":0.05}},{"duration":0,"tweenEasing":null,"transform":{}}],"name":"denglong1"},{"frame":[{"duration":19,"tweenEasing":0,"transform":{}},{"duration":20,"tweenEasing":0,"transform":{"skY":2.17,"skX":4.94,"scX":0.97,"scY":1.02}},{"duration":20,"tweenEasing":0,"transform":{"skY":8.39,"skX":8.39}},{"duration":20,"tweenEasing":0,"transform":{"y":0.05,"skY":7.87,"skX":5.16,"scX":1.03,"scY":0.99}},{"duration":0,"tweenEasing":null,"transform":{}}],"name":"denglong2"},{"frame":[{"duration":79,"tweenEasing":0,"transform":{}},{"duration":0,"tweenEasing":null,"transform":{}}],"name":"zhezhao"},{"frame":[{"duration":19,"tweenEasing":0,"transform":{}},{"duration":1,"tweenEasing":null,"transform":{"y":0.55,"x":5}},{"duration":39,"tweenEasing":0,"transform":{"y":117.5,"scX":0.3861,"scY":0.2506,"x":-219.1}},{"duration":20,"tweenEasing":0,"transform":{"y":0.55,"x":-11.75}},{"duration":0,"tweenEasing":null,"transform":{}}],"name":"diejiaguang"},{"frame":[{"duration":19,"tweenEasing":0,"transform":{"y":159.2,"skY":-29.99,"skX":-29.99,"scX":0.3968,"scY":0.2577,"x":-99.7}},{"duration":20,"tweenEasing":0,"transform":{"y":5,"skY":-29.99,"skX":-29.99,"x":21}},{"duration":20,"tweenEasing":0,"transform":{"y":5,"skY":-29.99,"skX":-29.99,"x":16}},{"duration":1,"tweenEasing":null,"transform":{"y":5,"skY":-29.99,"skX":-29.99,"x":21}},{"duration":19,"tweenEasing":null,"transform":{"y":159.2,"skY":-29.99,"skX":-29.99,"scX":0.3968,"scY":0.2577,"x":-99.7}}],"name":"diejiaguang2"},{"frame":[{"duration":79,"tweenEasing":null,"transform":{}}],"name":"root"},{"frame":[{"duration":79,"tweenEasing":null,"transform":{}}],"name":"mart_0"},{"frame":[{"duration":79,"tweenEasing":null,"transform":{}}],"name":"denglong1_0"},{"frame":[{"duration":79,"tweenEasing":null,"transform":{}}],"name":"denglong2_0"},{"frame":[{"duration":79,"tweenEasing":null,"transform":{}}],"name":"zhezhao_0"}],"playTimes":0,"name":"action1","ffd":[]},{"slot":[{"frame":[{"duration":5,"tweenEasing":0,"color":{}},{"duration":1,"tweenEasing":null,"color":{"aM":0}},{"duration":9,"tweenEasing":null,"displayIndex":-1,"color":{}}],"name":"diejiaguang2"},{"frame":[{"duration":5,"tweenEasing":0,"color":{}},{"duration":1,"tweenEasing":null,"color":{"aM":0}},{"duration":9,"tweenEasing":null,"displayIndex":-1,"color":{}}],"name":"diejiaguang"},{"frame":[{"duration":2,"tweenEasing":0,"color":{}},{"duration":3,"tweenEasing":0,"color":{"aM":90}},{"duration":3,"tweenEasing":0,"color":{"aM":50}},{"duration":3,"tweenEasing":0,"color":{"aM":25}},{"duration":1,"tweenEasing":null,"color":{"aM":0}},{"duration":3,"tweenEasing":null,"displayIndex":-1,"color":{}}],"name":"zhezhao_0"},{"frame":[{"duration":2,"tweenEasing":0,"color":{}},{"duration":3,"tweenEasing":0,"color":{"aM":90}},{"duration":3,"tweenEasing":0,"color":{"aM":50}},{"duration":3,"tweenEasing":0,"color":{"aM":25}},{"duration":1,"tweenEasing":null,"color":{"aM":0}},{"duration":3,"tweenEasing":null,"displayIndex":-1,"color":{}}],"name":"denglong2_0"},{"frame":[{"duration":2,"tweenEasing":0,"color":{}},{"duration":3,"tweenEasing":0,"color":{"aM":90}},{"duration":3,"tweenEasing":0,"color":{"aM":50}},{"duration":3,"tweenEasing":0,"color":{"aM":25}},{"duration":1,"tweenEasing":null,"color":{"aM":0}},{"duration":3,"tweenEasing":null,"displayIndex":-1,"color":{}}],"name":"denglong1_0"},{"frame":[{"duration":2,"tweenEasing":0,"color":{}},{"duration":3,"tweenEasing":0,"color":{"aM":90}},{"duration":3,"tweenEasing":0,"color":{"aM":50}},{"duration":3,"tweenEasing":0,"color":{"aM":25}},{"duration":1,"tweenEasing":null,"color":{"aM":0}},{"duration":3,"tweenEasing":null,"displayIndex":-1,"color":{}}],"name":"mart_0"},{"frame":[{"duration":2,"tweenEasing":0,"color":{}},{"duration":3,"tweenEasing":0,"color":{}},{"duration":3,"tweenEasing":0,"color":{}},{"duration":3,"tweenEasing":0,"color":{}},{"duration":4,"tweenEasing":0,"color":{}},{"duration":0,"tweenEasing":null,"color":{}}],"name":"zhezhao"},{"frame":[{"duration":2,"tweenEasing":0,"color":{}},{"duration":3,"tweenEasing":0,"color":{}},{"duration":3,"tweenEasing":0,"color":{}},{"duration":3,"tweenEasing":0,"color":{}},{"duration":4,"tweenEasing":0,"color":{}},{"duration":0,"tweenEasing":null,"color":{}}],"name":"denglong2"},{"frame":[{"duration":2,"tweenEasing":0,"color":{}},{"duration":3,"tweenEasing":0,"color":{}},{"duration":3,"tweenEasing":0,"color":{}},{"duration":3,"tweenEasing":0,"color":{}},{"duration":4,"tweenEasing":0,"color":{}},{"duration":0,"tweenEasing":null,"color":{}}],"name":"denglong1"},{"frame":[{"duration":2,"tweenEasing":0,"color":{}},{"duration":3,"tweenEasing":0,"color":{}},{"duration":3,"tweenEasing":0,"color":{}},{"duration":3,"tweenEasing":0,"color":{}},{"duration":4,"tweenEasing":0,"color":{}},{"duration":0,"tweenEasing":null,"color":{}}],"name":"mart"}],"fadeInTime":0.3,"frame":[],"duration":15,"bone":[{"frame":[{"duration":2,"tweenEasing":0,"transform":{"y":1.9,"scX":1.03,"scY":0.95}},{"duration":3,"tweenEasing":0,"transform":{"y":-1.6,"scX":0.98,"scY":1.04}},{"duration":3,"tweenEasing":0,"transform":{"y":0.75,"scX":1.03,"scY":0.98}},{"duration":3,"tweenEasing":0,"transform":{"y":-0.35,"scY":1.01}},{"duration":4,"tweenEasing":0,"transform":{"y":0.7,"scX":1.01,"scY":0.98}},{"duration":0,"tweenEasing":null,"transform":{}}],"name":"mart"},{"frame":[{"duration":2,"tweenEasing":0,"transform":{"y":0.15,"skY":42.94,"skX":39.2,"scX":1.03,"scY":0.95,"x":-0.8}},{"duration":3,"tweenEasing":0,"transform":{"y":-7.85,"skY":-0.4,"skX":-4.13,"scX":0.99,"scY":1.04,"x":10.65}},{"duration":3,"tweenEasing":0,"transform":{"y":0.8,"skY":-17.38,"skX":-18,"scX":1.03,"scY":0.98,"x":3.7}},{"duration":3,"tweenEasing":0,"transform":{"y":-1.5,"skY":-7.49,"skX":-7.39,"scY":1.01}},{"duration":4,"tweenEasing":0,"transform":{"y":2.8,"skY":8.6,"skX":8.33,"scX":1.01,"scY":0.98,"x":-0.6}},{"duration":0,"tweenEasing":null,"transform":{}}],"name":"denglong1"},{"frame":[{"duration":2,"tweenEasing":0,"transform":{"y":6.4,"skY":-31.61,"skX":-28.44,"scX":1.03,"scY":0.95,"x":-0.2}},{"duration":3,"tweenEasing":0,"transform":{"y":-10.25,"skY":23.4,"skX":23.84,"scX":0.98,"scY":1.04,"x":-1.4}},{"duration":3,"tweenEasing":0,"transform":{"y":-7.4,"skY":33.72,"skX":33.14,"scX":1.03,"scY":0.98,"x":-3.2}},{"duration":3,"tweenEasing":0,"transform":{"y":-1.2,"skY":18.17,"skX":18.27,"scY":1.01}},{"duration":4,"tweenEasing":0,"transform":{"y":2.2,"skY":-3.34,"skX":-3.59,"scX":1.01,"scY":0.98}},{"duration":0,"tweenEasing":null,"transform":{}}],"name":"denglong2"},{"frame":[{"duration":2,"tweenEasing":0,"transform":{"y":7.65,"scX":1.03,"scY":0.95,"x":-0.5}},{"duration":3,"tweenEasing":0,"transform":{"y":-6.25,"scX":0.985,"scY":1.04,"x":0.25}},{"duration":3,"tweenEasing":0,"transform":{"y":3.15,"scX":1.03,"scY":0.98,"x":-0.5}},{"duration":3,"tweenEasing":0,"transform":{"y":-1.4,"scY":1.01}},{"duration":4,"tweenEasing":0,"transform":{"y":2.65,"scX":1.005,"scY":0.985,"x":-0.05}},{"duration":0,"tweenEasing":null,"transform":{}}],"name":"zhezhao"},{"frame":[{"duration":2,"tweenEasing":0,"transform":{}},{"duration":3,"tweenEasing":0,"transform":{"y":-3.5,"scX":0.9515,"scY":1.0947}},{"duration":3,"tweenEasing":0,"transform":{"y":-1.15,"scY":1.0316}},{"duration":3,"tweenEasing":0,"transform":{"y":-2.25,"scX":0.9709,"scY":1.0632}},{"duration":1,"tweenEasing":null,"transform":{"y":-1.2,"scX":0.9806,"scY":1.0316}},{"duration":3,"tweenEasing":null,"transform":{"y":64.6,"scX":0.9709,"scY":1.0526,"x":-223}}],"name":"mart_0"},{"frame":[{"duration":2,"tweenEasing":0,"transform":{}},{"duration":3,"tweenEasing":0,"transform":{"y":-8,"skY":-43.34,"skX":-43.33,"scX":0.9612,"scY":1.0947,"x":11.45}},{"duration":3,"tweenEasing":0,"transform":{"y":0.65,"skY":-60.32,"skX":-57.2,"scY":1.0316,"x":4.5}},{"duration":3,"tweenEasing":0,"transform":{"y":-1.65,"skY":-50.43,"skX":-46.59,"scX":0.9709,"scY":1.0632,"x":0.8}},{"duration":1,"tweenEasing":null,"transform":{"y":2.65,"skY":-34.34,"skX":-30.87,"scX":0.9806,"scY":1.0316,"x":0.2}},{"duration":3,"tweenEasing":null,"transform":{"y":193.35,"skY":-36.97,"skX":-33.23,"scX":0.9709,"scY":1.0526,"x":-119.25}}],"name":"denglong1_0"},{"frame":[{"duration":2,"tweenEasing":0,"transform":{}},{"duration":3,"tweenEasing":0,"transform":{"y":-16.65,"skY":55.01,"skX":52.28,"scX":0.9515,"scY":1.0947,"x":-1.2}},{"duration":3,"tweenEasing":0,"transform":{"y":-13.8,"skY":65.33,"skX":61.58,"scY":1.0316,"x":-3}},{"duration":3,"tweenEasing":0,"transform":{"y":-7.6,"skY":49.78,"skX":46.71,"scX":0.9709,"scY":1.0632,"x":0.2}},{"duration":1,"tweenEasing":null,"transform":{"y":-4.2,"skY":28.27,"skX":24.85,"scX":0.9806,"scY":1.0316,"x":0.2}},{"duration":3,"tweenEasing":null,"transform":{"y":151.55,"skY":37.3,"skX":34.13,"scX":0.9709,"scY":1.0526,"x":-217.35}}],"name":"denglong2_0"},{"frame":[{"duration":2,"tweenEasing":0,"transform":{}},{"duration":3,"tweenEasing":0,"transform":{"y":-13.9,"scX":0.9563,"scY":1.0947,"x":0.75}},{"duration":3,"tweenEasing":0,"transform":{"y":-4.5,"scY":1.0316}},{"duration":3,"tweenEasing":0,"transform":{"y":-9.05,"scX":0.9709,"scY":1.0632,"x":0.5}},{"duration":1,"tweenEasing":null,"transform":{"y":-5,"scX":0.9757,"scY":1.0368,"x":0.45}},{"duration":3,"tweenEasing":null,"transform":{"y":175.35,"scX":0.4854,"scY":0.5263,"x":-207.55}}],"name":"zhezhao_0"},{"frame":[{"duration":5,"tweenEasing":0,"transform":{"y":2,"skY":-33.46,"skX":-33.46,"x":17}},{"duration":1,"tweenEasing":null,"transform":{"y":2,"skY":-33.46,"skX":-33.46,"scX":2,"scY":1.9975,"x":17}},{"duration":9,"tweenEasing":null,"transform":{"y":117.5,"scX":0.3861,"scY":0.2506,"x":-219.1}}],"name":"diejiaguang"},{"frame":[{"duration":5,"tweenEasing":0,"transform":{}},{"duration":1,"tweenEasing":null,"transform":{"scX":2,"scY":2}},{"duration":9,"tweenEasing":null,"transform":{"y":159.2,"skY":-29.99,"skX":-29.99,"scX":0.3968,"scY":0.2577,"x":-99.7}}],"name":"diejiaguang2"},{"frame":[{"duration":15,"tweenEasing":null,"transform":{}}],"name":"root"}],"name":"action2","ffd":[]}],"aabb":{"width":263.99777931364974,"y":-251.5,"height":229.55,"x":83.50222068635026}}],"frameRate":30,"isGlobal":0,"name":"blackmart_ske","version":"4.5"}